json_server/__init__.py
json_server/main.py
json_server-0.1.3.dist-info/METADATA
json_server-0.1.3.dist-info/WHEEL
json_server-0.1.3.dist-info/entry_points.txt
json_server-0.1.3.dist-info/top_level.txt
json_server-0.1.3.dist-info/RECORD
