Metadata-Version: 2.1
Name: json-server
Version: 0.1.3
Summary: UNKNOWN
Home-page: https://github.com/YuvrajGeek/json-server
License: UNKNOWN
Platform: UNKNOWN
Requires-Dist: click
Requires-Dist: flask
Requires-Dist: flask-cors
